{"nodes": [{"id": "src_pages_driverhistory_tsx", "label": "DriverHistory.tsx", "file_type": "code", "source_file": "src\\pages\\DriverHistory.tsx", "source_location": "L1"}, {"id": "driverhistory_fetchshifts", "label": "fetchShifts()", "file_type": "code", "source_file": "src\\pages\\DriverHistory.tsx", "source_location": "L19"}, {"id": "driverhistory_formatduration", "label": "formatDuration()", "file_type": "code", "source_file": "src\\pages\\DriverHistory.tsx", "source_location": "L41"}, {"id": "driverhistory_handledownload", "label": "handleDownload()", "file_type": "code", "source_file": "src\\pages\\DriverHistory.tsx", "source_location": "L60"}], "edges": [{"source": "src_pages_driverhistory_tsx", "target": "react", "relation": "imports_from", "confidence": "EXTRACTED", "source_file": "src\\pages\\DriverHistory.tsx", "source_location": "L1", "weight": 1.0}, {"source": "src_pages_driverhistory_tsx", "target": "lucide_react", "relation": "imports_from", "confidence": "EXTRACTED", "source_file": "src\\pages\\DriverHistory.tsx", "source_location": "L2", "weight": 1.0}, {"source": "src_pages_driverhistory_tsx", "target": "src_components_ui_button", "relation": "imports_from", "confidence": "EXTRACTED", "source_file": "src\\pages\\DriverHistory.tsx", "source_location": "L3", "weight": 1.0}, {"source": "src_pages_driverhistory_tsx", "target": "src_components_ui_badge", "relation": "imports_from", "confidence": "EXTRACTED", "source_file": "src\\pages\\DriverHistory.tsx", "source_location": "L4", "weight": 1.0}, {"source": "src_pages_driverhistory_tsx", "target": "src_components_ui_input", "relation": "imports_from", "confidence": "EXTRACTED", "source_file": "src\\pages\\DriverHistory.tsx", "source_location": "L5", "weight": 1.0}, {"source": "src_pages_driverhistory_tsx", "target": "src_lib_api", "relation": "imports_from", "confidence": "EXTRACTED", "source_file": "src\\pages\\DriverHistory.tsx", "source_location": "L6", "weight": 1.0}, {"source": "src_pages_driverhistory_tsx", "target": "date_fns", "relation": "imports_from", "confidence": "EXTRACTED", "source_file": "src\\pages\\DriverHistory.tsx", "source_location": "L7", "weight": 1.0}, {"source": "src_pages_driverhistory_tsx", "target": "driverhistory_fetchshifts", "relation": "contains", "confidence": "EXTRACTED", "source_file": "src\\pages\\DriverHistory.tsx", "source_location": "L19", "weight": 1.0}, {"source": "src_pages_driverhistory_tsx", "target": "driverhistory_formatduration", "relation": "contains", "confidence": "EXTRACTED", "source_file": "src\\pages\\DriverHistory.tsx", "source_location": "L41", "weight": 1.0}, {"source": "src_pages_driverhistory_tsx", "target": "driverhistory_handledownload", "relation": "contains", "confidence": "EXTRACTED", "source_file": "src\\pages\\DriverHistory.tsx", "source_location": "L60", "weight": 1.0}], "raw_calls": [{"caller_nid": "driverhistory_fetchshifts", "callee": "getShifts", "source_file": "src\\pages\\DriverHistory.tsx", "source_location": "L23"}, {"caller_nid": "driverhistory_fetchshifts", "callee": "filter", "source_file": "src\\pages\\DriverHistory.tsx", "source_location": "L26"}, {"caller_nid": "driverhistory_fetchshifts", "callee": "setShifts", "source_file": "src\\pages\\DriverHistory.tsx", "source_location": "L27"}, {"caller_nid": "driverhistory_fetchshifts", "callee": "error", "source_file": "src\\pages\\DriverHistory.tsx", "source_location": "L29"}, {"caller_nid": "driverhistory_fetchshifts", "callee": "setLoading", "source_file": "src\\pages\\DriverHistory.tsx", "source_location": "L31"}, {"caller_nid": "driverhistory_formatduration", "callee": "getTime", "source_file": "src\\pages\\DriverHistory.tsx", "source_location": "L43"}, {"caller_nid": "driverhistory_formatduration", "callee": "getTime", "source_file": "src\\pages\\DriverHistory.tsx", "source_location": "L44"}, {"caller_nid": "driverhistory_formatduration", "callee": "getTime", "source_file": "src\\pages\\DriverHistory.tsx", "source_location": "L44"}, {"caller_nid": "driverhistory_formatduration", "callee": "floor", "source_file": "src\\pages\\DriverHistory.tsx", "source_location": "L46"}, {"caller_nid": "driverhistory_formatduration", "callee": "floor", "source_file": "src\\pages\\DriverHistory.tsx", "source_location": "L47"}, {"caller_nid": "driverhistory_handledownload", "callee": "createElement", "source_file": "src\\pages\\DriverHistory.tsx", "source_location": "L61"}, {"caller_nid": "driverhistory_handledownload", "callee": "appendChild", "source_file": "src\\pages\\DriverHistory.tsx", "source_location": "L64"}, {"caller_nid": "driverhistory_handledownload", "callee": "click", "source_file": "src\\pages\\DriverHistory.tsx", "source_location": "L65"}, {"caller_nid": "driverhistory_handledownload", "callee": "removeChild", "source_file": "src\\pages\\DriverHistory.tsx", "source_location": "L66"}]}